{"nodes": {"351": {"grain_type": 0, "rle": {"size": [512, 512], "counts": "_]f11k?9H5K4N2N2J6M4L3N2O1N100O101O1N2N1N10100000001N10001N2O000O1O100000O1O2N2N2O1O001O001O1O1N3M2L4K4O2N3K4L4M3N3G^@NbR^5"}, "grain_size": [[2184, 0]]}, "306": {"grain_type": 1, "rle": {"size": [512, 512], "counts": "a[d18_?;L3N1N3N3M4L2O6J1N2N10001O001O1N2O0000001N2O1O00000000O10001N2O002M3M2O1O1O1N2M3N2N2N2N2N2WOQA?Y?N4L3M2NTTb5"}, "grain_size": [[1978, 8732]]}, "333": {"grain_type": 1, "rle": {"size": [512, 512], "counts": "^\\h14j?3Y@Ja?<O1O10N101N2O1N10000O2N2MaSP6"}, "grain_size": [[139, 0]]}, "335": {"grain_type": 2, "rle": {"size": [512, 512], "counts": "]lW21m?3N2N2N2N1O2O0O2N2N2N3M2O1O001O2M2O1O101N1N10O01O100001O1N2O1N2M3N1O2@m@1e?L3LWSU5"}, "grain_size": [[868, 0]]}, "342": {"grain_type": 1, "rle": {"size": [512, 512], "counts": "mlY12m?2N2M3L4N4L3M3M1N3O00010O0O101O00001O001N1O20O000O1L4M4L5M2Ab@9d?J6MYcU6"}, "grain_size": [[739, 0]]}, "350": {"grain_type": 1, "rle": {"size": [512, 512], "counts": "Vma232Od?9O1N2O1OO1O1O1O0O2N102N2NoRW5"}, "grain_size": [[143, 0]]}, "355": {"grain_type": 1, "rle": {"size": [512, 512], "counts": "lm]24h?5N1O0N2N2O1001O2L4N2N2N2N_R[5"}, "grain_size": [[133, 0]]}, "365": {"grain_type": 1, "rle": {"size": [512, 512], "counts": "g]W11n?3M5K2N2M5L2N3M2M2O1O100001O000010O00010O1O01O0O2N1O2N1O100O6J3M2O1O1N2N3MTbU6"}, "grain_size": [[766, 0]]}, "375": {"grain_type": 1, "rle": {"size": [512, 512], "counts": "T^W23l?6J2N3N1O1O00O100O1O01O11O1O2L4KnQ`5"}, "grain_size": [[210, 0]]}, "383": {"grain_type": 1, "rle": {"size": [512, 512], "counts": "Y^c16i?:F2N2N2O1N2N2N2O2N1N2N2N1O02O1O00000O2O1O1N10O1000000001O00010O1M200O1O1O1O1O3M6I3N3M2KdQf5"}, "grain_size": [[1193, 0]]}, "278": {"grain_type": 1, "rle": {"size": [512, 512], "counts": "_jn13l?7I5K1O1O1O1J6O1O10100O00O1O1O1O1O1N3N3J6M2N2NhUe5"}, "grain_size": [[462, 0]]}, "282": {"grain_type": 1, "rle": {"size": [512, 512], "counts": "mZU23l?3M2N2N2M3N2K5N2N2N2I7O1O00000000000000O10000000001O1O1J5L8J3N2M4M2N2N2NZUX5"}, "grain_size": [[889, 0]]}, "291": {"grain_type": 1, "rle": {"size": [512, 512], "counts": "fZd13l?5K2N1N3N2N2L2O2000O1O101O001O001N2O00004L6IYUP6"}, "grain_size": [[355, 0]]}, "305": {"grain_type": 1, "rle": {"size": [512, 512], "counts": "W[T16i?3N1N1O101O1O1N2O2N1N2M2O1O01O01O001O2N1000O101N1000O100O10O101M6C:M2O2M3NQeX6"}, "grain_size": [[754, 0]]}, "307": {"grain_type": 1, "rle": {"size": [512, 512], "counts": "^[[28g?2O3M2N1O4L000O1000O100001O00O2O1N2N2O1L4M3N3L]dX5"}, "grain_size": [[374, 0]]}, "319": {"grain_type": 1, "rle": {"size": [512, 512], "counts": "okV13l?1O2N3M2M2O2O1O1N2N101N01101N3M0O101N10O10000000O1006I3L3N1O2N3N3L2OmcW6"}, "grain_size": [[662, 0]]}, "329": {"grain_type": 1, "rle": {"size": [512, 512], "counts": "]ld11n?2N1O100O101ON3MhcV6"}, "grain_size": [[38, 0]]}, "310": {"grain_type": 1, "rle": {"size": [512, 512], "counts": "k[e23k?3N2M3O1O1O1N1O2O10O00O10O2N2N2N6J2NTTQ5"}, "grain_size": [[233, 0]]}, "326": {"grain_type": 1, "rle": {"size": [512, 512], "counts": "]\\i26c?;L3M1O0O1O2N1O2N1O1M3O10L4O1O2L4L3N2O1J7N3LQTk4"}, "grain_size": [[486, 0]]}, "343": {"grain_type": 1, "rle": {"size": [512, 512], "counts": "nlg23l?2N2OO10O2OO10001O001O000O1OTcP5"}, "grain_size": [[85, 0]]}, "331": {"grain_type": 1, "rle": {"size": [512, 512], "counts": "X\\m05j?2N2M3N2N2N2N2N2N101O1O1O100O000001O2N001O2O0O01000N2N2M2M4N002N3Mdca6"}, "grain_size": [[638, 0]]}, "349": {"grain_type": 1, "rle": {"size": [512, 512], "counts": "Smm05j?2N2N2O1N2M3N3N1N2N101N200O00001O001O00O2N1O2N4K3N2N2N2M5L3Mibb6"}, "grain_size": [[588, 0]]}, "363": {"grain_type": 1, "rle": {"size": [512, 512], "counts": "`]d22m?2N2N2M3M3N2N2N2L4N2O100N2O2N1O1O1O1OO000O2O2N2O1O001O1O1000O0001N2M3N2J5N3K5Ndbg4"}, "grain_size": [[900, 0]]}, "380": {"grain_type": 1, "rle": {"size": [512, 512], "counts": "Qn^2291X?2c@2[?;N3M3M2N2L4N1O1O1O0002N2O1O1N200O1N2Jl@]OV?a06O1N2N3M2L4N2NmaR5"}, "grain_size": [[652, 0]]}, "369": {"grain_type": 1, "rle": {"size": [512, 512], "counts": "f]d01n?9F2O1O2N102M2N2N2O1N2N3N1O1O1N1O1O1001O1N2N2O1O101N1O1O010N2O1O000010O010001M5K2N2N4L2N3Mkad6"}, "grain_size": [[1028, 4851]]}, "376": {"grain_type": 2, "rle": {"size": [512, 512], "counts": "]nW12m?3M3M4_@GT?c0O1O2O1O00O1O10000O1O101N1O101O1N100O6JbQ\\6"}, "grain_size": [[448, 0]]}, "396": {"grain_type": 1, "rle": {"size": [512, 512], "counts": "PoS23m?1N2N3M2N3M2N1N2O001L4O01O0010O1O010000O101O1N2N3M3M2M3K5NYQ]5"}, "grain_size": [[499, 0]]}, "398": {"grain_type": 1, "rle": {"size": [512, 512], "counts": "]_g13h?6N3M2M200O10001O000O2O1O1N100000001O00O1O1O2N1O2N2M3N3L3N3MgPi5"}, "grain_size": [[518, 0]]}, "400": {"grain_type": 1, "rle": {"size": [512, 512], "counts": "Qo[12m?4L10000O2N100O2N101O1N100O2N2O1000O1O1O1O1O1N3I6N2Nn`V6"}, "grain_size": [[343, 0]]}}, "edges": {"(351, 306)": {}, "(351, 333)": {}, "(351, 335)": {}, "(351, 342)": {}, "(351, 350)": {}, "(351, 355)": {}, "(351, 365)": {}, "(351, 375)": {}, "(351, 383)": {}, "(306, 278)": {}, "(306, 282)": {}, "(306, 291)": {}, "(306, 305)": {}, "(306, 307)": {}, "(306, 319)": {}, "(306, 329)": {}, "(306, 333)": {}, "(306, 335)": {}, "(306, 351)": {}, "(333, 306)": {}, "(333, 329)": {}, "(333, 342)": {}, "(333, 351)": {}, "(335, 306)": {}, "(335, 307)": {}, "(335, 310)": {}, "(335, 326)": {}, "(335, 343)": {}, "(335, 350)": {}, "(335, 351)": {}, "(342, 319)": {}, "(342, 329)": {}, "(342, 331)": {}, "(342, 333)": {}, "(342, 349)": {}, "(342, 351)": {}, "(342, 365)": {}, "(350, 335)": {}, "(350, 343)": {}, "(350, 351)": {}, "(350, 355)": {}, "(350, 363)": {}, "(355, 350)": {}, "(355, 351)": {}, "(355, 363)": {}, "(355, 375)": {}, "(355, 380)": {}, "(365, 342)": {}, "(365, 349)": {}, "(365, 351)": {}, "(365, 369)": {}, "(365, 376)": {}, "(365, 383)": {}, "(375, 351)": {}, "(375, 355)": {}, "(375, 380)": {}, "(375, 383)": {}, "(375, 396)": {}, "(383, 351)": {}, "(383, 365)": {}, "(383, 375)": {}, "(383, 376)": {}, "(383, 396)": {}, "(383, 398)": {}, "(383, 400)": {}, "(278, 282)": {}, "(278, 291)": {}, "(278, 306)": {}, "(282, 278)": {}, "(282, 306)": {}, "(282, 307)": {}, "(291, 278)": {}, "(291, 305)": {}, "(291, 306)": {}, "(305, 291)": {}, "(305, 306)": {}, "(305, 319)": {}, "(307, 282)": {}, "(307, 306)": {}, "(307, 310)": {}, "(307, 335)": {}, "(319, 305)": {}, "(319, 306)": {}, "(319, 329)": {}, "(319, 331)": {}, "(319, 342)": {}, "(329, 306)": {}, "(329, 319)": {}, "(329, 333)": {}, "(329, 342)": {}, "(310, 307)": {}, "(310, 326)": {}, "(310, 335)": {}, "(326, 310)": {}, "(326, 335)": {}, "(326, 343)": {}, "(343, 326)": {}, "(343, 335)": {}, "(343, 350)": {}, "(343, 363)": {}, "(331, 319)": {}, "(331, 342)": {}, "(331, 349)": {}, "(349, 331)": {}, "(349, 342)": {}, "(349, 365)": {}, "(349, 369)": {}, "(363, 343)": {}, "(363, 350)": {}, "(363, 355)": {}, "(363, 380)": {}, "(380, 355)": {}, "(380, 363)": {}, "(380, 375)": {}, "(380, 396)": {}, "(369, 349)": {}, "(369, 365)": {}, "(369, 376)": {}, "(376, 365)": {}, "(376, 369)": {}, "(376, 383)": {}, "(376, 400)": {}, "(396, 375)": {}, "(396, 380)": {}, "(396, 383)": {}, "(396, 398)": {}, "(398, 383)": {}, "(398, 396)": {}, "(398, 400)": {}, "(400, 376)": {}, "(400, 383)": {}, "(400, 398)": {}}, "metadata": {"subgraph_metadata": [{"img_size": [512, 512], "grain_types": {"type_0": [[1.0, 0.0, 0.0], "candidate grain (white)"], "type_1": [[0.8944271802902222, 0.4472135901451111, 0.0], "low mobility (blue)"], "type_2": [[0.5773502588272095, 0.5773502588272095, 0.5773502588272095], "high mobility (red)"]}, "path": ["/media/ryan/TOSHIBA EXT/Research/datasets/AFRL_AGG/SPPARKS_simulations/candidate-grains/2020_12_29_00_38_candidate_grains_master/spparks_results/run_805"], "timesteps": [[0.0, 2000.0, 4000000.0]]}], "subgraph_node_ranges": [423]}}