{"nodes": {"109": {"grain_type": 0, "rle": {"size": [512, 512], "counts": "kSk21n?5K2Z@O[?2c@0[?;O3M3L3N2E;O1O3L2N2O001O1O0O2N1O01O01O11O1O001O1O00O1000000001O001O1N2N1L5N2M3N2M2O1O100O2N1O2N2Bl@MV?JXAOX[Z4"}, "grain_size": [[2185, 66244]]}, "66": {"grain_type": 2, "rle": {"size": [512, 512], "counts": "abb22m?2N2L4N5HCd@>[?401N2N2O1N2O1O2M3M100O1O2N101N2N2N100O2O01O1O1N2N2O1O1O1O1N2N3M2O3L2N2O6I3J7L3LY]f4"}, "grain_size": [[1341, 0]]}, "74": {"grain_type": 1, "rle": {"size": [512, 512], "counts": "RSW31n?2K4O2M3N10O101O00000M3M3OWma4"}, "grain_size": [[119, 0]]}, "83": {"grain_type": 1, "rle": {"size": [512, 512], "counts": "Rc\\34i?3O2K5O1O0O2O1O1O1O000O1O101N101O1O1O10M3N1O2M3L4M3H\\@1k?N2NnlT4"}, "grain_size": [[503, 0]]}, "91": {"grain_type": 2, "rle": {"size": [512, 512], "counts": "]cf27h?3M2N4L1L4O2O000001N1O2O1N2N1O1N3Nh\\P5"}, "grain_size": [[303, 0]]}, "95": {"grain_type": 2, "rle": {"size": [512, 512], "counts": "kSe34d?>I1N3N2N2M3L4M3N2N2N101O1O4L2N2M2O1O10O0000002N3N1M2O2M2N2M3M3N2O1N2N2N2N2N2N2N2I7N2M3MT\\d3"}, "grain_size": [[1554, 0]]}, "111": {"grain_type": 2, "rle": {"size": [512, 512], "counts": "Tdb22n?2M2O0N3N2N2N2N1O2M201O00O2O00001N5K2G9NokR5"}, "grain_size": [[272, 0]]}, "121": {"grain_type": 1, "rle": {"size": [512, 512], "counts": "jd]31n?4L2K5N1N3N2M101O01O0001O1O2N2N1O11O100O100O10000O010N2O4K3M3N1N2MY[Q4"}, "grain_size": [[630, 0]]}, "125": {"grain_type": 1, "rle": {"size": [512, 512], "counts": "_dh23l?2O2N1O0O1O1O110O11N2N1O1N2O1O\\[o4"}, "grain_size": [[121, 0]]}, "138": {"grain_type": 1, "rle": {"size": [512, 512], "counts": "Ye`24k?3M4K4N001O1N2N1O2N1O2N1O2N2N1M3O1M310O00000001O10O001O0O0100O1O2M3N1O2M3Fm@DT?Nk@OO48KP?0j[k4"}, "grain_size": [[1098, 0]]}, "140": {"grain_type": 1, "rle": {"size": [512, 512], "counts": "\\US33_?Oc@O48U?=N2N1O2O1O00001O1O1O1O2N1O1O1O00000001N4L2N2N101O1O5K0O2L4L4N2L4NeZ[4"}, "grain_size": [[891, 0]]}, "37": {"grain_type": 2, "rle": {"size": [512, 512], "counts": "fa]24k?1O2N2N1L5M3N2N3M2M4M20000O10N2N101N1O2O1N101O0O1O100O1O2N2O1N2N2N2O1N2OZno4"}, "grain_size": [[684, 0]]}, "43": {"grain_type": 2, "rle": {"size": [512, 512], "counts": "oaZ21n?2N3M6J4a@AV?e001O01O1O001000001M2O2L3N2N2L4N2Nh]Z5"}, "grain_size": [[311, 0]]}, "58": {"grain_type": 1, "rle": {"size": [512, 512], "counts": "eQP36i?2N2N2N2N2N2L4K5N2N3O002M100O6K1O2M2OO00O101O01OO10000O100000O100000001O0O2N2O0O1000000G:N2L4N2N2N1N3N2N1N3N2N2J^^S4"}, "grain_size": [[1873, 0]]}, "61": {"grain_type": 1, "rle": {"size": [512, 512], "counts": "cba27i?1O1000N2N[][5"}, "grain_size": [[45, 0]]}, "79": {"grain_type": 1, "rle": {"size": [512, 512], "counts": "Qcb29c?5N2N2N10000100N2N2N2N2N3JR]V5"}, "grain_size": [[201, 0]]}, "63": {"grain_type": 1, "rle": {"size": [512, 512], "counts": "]Rf39f?2L4N1O2N2M3N2l@XOm>o0M3N2N1K5N200O010O101O00000001N3N1N1O2O000kNYAQ1m>M2O2N1O1O1G8O1Id@H^?59N1O2N101Ogmc3"}, "grain_size": [[1283, 0]]}, "94": {"grain_type": 1, "rle": {"size": [512, 512], "counts": "hS\\24k?2N7I2M2O1N3N1O1O1O1O1O10O2O1N2O0N2O1O2N7I3M2M[lW5"}, "grain_size": [[428, 0]]}, "87": {"grain_type": 2, "rle": {"size": [512, 512], "counts": "TSQ42m?4M2M2N3N1O1O1N2O1O1O1O1O1000000000000000N2M3N2O1N100O3M2O4L]\\_3"}, "grain_size": [[497, 0]]}, "105": {"grain_type": 1, "rle": {"size": [512, 512], "counts": "VdY46i?2M3M3K4N2O2O1N2OO00010O1000001O000O2N2N1O1O2O5K6J1NjkX3"}, "grain_size": [[486, 0]]}, "123": {"grain_type": 2, "rle": {"size": [512, 512], "counts": "iTS43l?5J3M2O100O1O1O1O1O1O001001O1O1N1H8O2M3N`[b3"}, "grain_size": [[281, 0]]}, "131": {"grain_type": 1, "rle": {"size": [512, 512], "counts": "Qem31m?3J6O1OO100O1O2OO10O3MU[l3"}, "grain_size": [[89, 0]]}, "108": {"grain_type": 1, "rle": {"size": [512, 512], "counts": "TT^26j?01O0000000001O01N3Mi[\\5"}, "grain_size": [[54, 0]]}, "129": {"grain_type": 1, "rle": {"size": [512, 512], "counts": "fdY21n?2U@2a?9M6I2M3O1O1O2N101O00001OO1O2N1N11O1000O2N2N2N2N1O2N1O2N4J4N^[V5"}, "grain_size": [[714, 0]]}, "137": {"grain_type": 1, "rle": {"size": [512, 512], "counts": "QUa36j?0O2N2N2O1O1000N1O10001N101N101O1M2OmZU4"}, "grain_size": [[171, 0]]}, "150": {"grain_type": 1, "rle": {"size": [512, 512], "counts": "gUb34i?4N3K4N1N3N2N2O1O1N100O10000N10001O01O01O01O1O2I7N2L6Jkjo3"}, "grain_size": [[614, 0]]}, "147": {"grain_type": 1, "rle": {"size": [512, 512], "counts": "gUS22m?2N1O2N2M3N2N1O1O1N2O2OO01O010O10O100O1O2N101N100O2O3L3M4L_j]5"}, "grain_size": [[435, 0]]}, "162": {"grain_type": 1, "rle": {"size": [512, 512], "counts": "nen22m?2O1N<D1N2O1O1N2O001001O0O2N2N1O1O2N2N2N2N3M2N2NSjd4"}, "grain_size": [[389, 0]]}, "170": {"grain_type": 1, "rle": {"size": [512, 512], "counts": "meg2?_?3O1O1O3N0O1O1OO1O1O2N1O2O2M2N2Noio4"}, "grain_size": [[332, 0]]}, "173": {"grain_type": 1, "rle": {"size": [512, 512], "counts": "SVT23l?3M3M2N5K2O1O3M101M6K1N10000O2O1N2N3M2O1N100O2O1N2N2N10O1O2O1O1O0O2N101O0O2O1iNgAe0k>N2N2O3J4N2JaiT5"}, "grain_size": [[1486, 0]]}, "176": {"grain_type": 1, "rle": {"size": [512, 512], "counts": "[VU32m?2N3M2N2N2^@MT?`0O1O1O1O1O2N2O0000001N2N2N2N2O1O00O1O011N2O2N1O001O1N2N2O1I6N2\\Oj@7YYX4"}, "grain_size": [[1158, 0]]}}, "edges": {"(109, 66)": {}, "(109, 74)": {}, "(109, 83)": {}, "(109, 91)": {}, "(109, 95)": {}, "(109, 111)": {}, "(109, 121)": {}, "(109, 125)": {}, "(109, 138)": {}, "(109, 140)": {}, "(66, 37)": {}, "(66, 43)": {}, "(66, 58)": {}, "(66, 61)": {}, "(66, 74)": {}, "(66, 79)": {}, "(66, 91)": {}, "(66, 109)": {}, "(74, 58)": {}, "(74, 66)": {}, "(74, 83)": {}, "(74, 109)": {}, "(83, 58)": {}, "(83, 63)": {}, "(83, 74)": {}, "(83, 95)": {}, "(83, 109)": {}, "(91, 66)": {}, "(91, 79)": {}, "(91, 94)": {}, "(91, 109)": {}, "(91, 111)": {}, "(95, 63)": {}, "(95, 83)": {}, "(95, 87)": {}, "(95, 105)": {}, "(95, 109)": {}, "(95, 121)": {}, "(95, 123)": {}, "(95, 131)": {}, "(111, 91)": {}, "(111, 94)": {}, "(111, 108)": {}, "(111, 109)": {}, "(111, 125)": {}, "(111, 129)": {}, "(121, 95)": {}, "(121, 109)": {}, "(121, 131)": {}, "(121, 137)": {}, "(121, 140)": {}, "(121, 150)": {}, "(125, 109)": {}, "(125, 111)": {}, "(125, 129)": {}, "(125, 138)": {}, "(138, 109)": {}, "(138, 125)": {}, "(138, 129)": {}, "(138, 140)": {}, "(138, 147)": {}, "(138, 162)": {}, "(138, 170)": {}, "(138, 173)": {}, "(140, 109)": {}, "(140, 121)": {}, "(140, 137)": {}, "(140, 138)": {}, "(140, 150)": {}, "(140, 162)": {}, "(140, 176)": {}, "(37, 43)": {}, "(37, 58)": {}, "(37, 66)": {}, "(43, 37)": {}, "(43, 61)": {}, "(43, 66)": {}, "(58, 37)": {}, "(58, 63)": {}, "(58, 66)": {}, "(58, 74)": {}, "(58, 83)": {}, "(61, 43)": {}, "(61, 66)": {}, "(61, 79)": {}, "(79, 61)": {}, "(79, 66)": {}, "(79, 91)": {}, "(79, 94)": {}, "(63, 58)": {}, "(63, 83)": {}, "(63, 87)": {}, "(63, 95)": {}, "(94, 79)": {}, "(94, 91)": {}, "(94, 108)": {}, "(94, 111)": {}, "(87, 63)": {}, "(87, 95)": {}, "(87, 105)": {}, "(105, 87)": {}, "(105, 95)": {}, "(105, 123)": {}, "(123, 95)": {}, "(123, 105)": {}, "(123, 131)": {}, "(131, 95)": {}, "(131, 121)": {}, "(131, 123)": {}, "(131, 150)": {}, "(108, 94)": {}, "(108, 111)": {}, "(108, 129)": {}, "(129, 108)": {}, "(129, 111)": {}, "(129, 125)": {}, "(129, 138)": {}, "(129, 147)": {}, "(137, 121)": {}, "(137, 140)": {}, "(137, 150)": {}, "(150, 121)": {}, "(150, 131)": {}, "(150, 137)": {}, "(150, 140)": {}, "(150, 176)": {}, "(147, 129)": {}, "(147, 138)": {}, "(147, 173)": {}, "(162, 138)": {}, "(162, 140)": {}, "(162, 170)": {}, "(162, 176)": {}, "(170, 138)": {}, "(170, 162)": {}, "(170, 173)": {}, "(173, 138)": {}, "(173, 147)": {}, "(173, 170)": {}, "(176, 140)": {}, "(176, 150)": {}, "(176, 162)": {}}, "metadata": {"subgraph_metadata": [{"img_size": [512, 512], "grain_types": {"type_0": [[1.0, 0.0, 0.0], "candidate grain (white)"], "type_1": [[0.8944271802902222, 0.4472135901451111, 0.0], "low mobility (blue)"], "type_2": [[0.5773502588272095, 0.5773502588272095, 0.5773502588272095], "high mobility (red)"]}, "path": ["/media/ryan/TOSHIBA EXT/Research/datasets/AFRL_AGG/SPPARKS_simulations/candidate-grains/2021_01_29_22_32_candidate_grains_master/spparks_results/run_431"], "timesteps": [[0.0, 2000.0, 4000000.0]]}], "subgraph_node_ranges": [446]}}