{"nodes": {"405": {"grain_type": 0, "rle": {"size": [512, 512], "counts": "Qo31m?3N4L2O1N2M3N2N3J6M3J6L3N2M2L5O0O1O1O001O1M3N2N101000000O100O1001OO10000010O1O1O0O2N2N2N2N1O1FcAPO_>m0eAPO]>n0<N2N2N2N2N2O1N2N2K5H8N2NeQm6"}, "grain_size": [[2467, 27431]]}, "4": {"grain_type": 1, "rle": {"size": [512, 512], "counts": "PP41n?7I2N2M4M2N3N1O0O100O1O1O1010O000000O1000001O0O101O0000001O000000001O0010O01OO2N2N5K2N1O2N1M3O1O2E]@6j?L2NloQ7"}, "grain_size": [[1215, 0]]}, "379": {"grain_type": 1, "rle": {"size": [512, 512], "counts": "h]43d?3^@O`?9O2N2O1N101O1O10000O1O11N1O1N1O2N2N1O1M2O8HZb_7"}, "grain_size": [[415, 0]]}, "380": {"grain_type": 1, "rle": {"size": [512, 512], "counts": "bm?6i?2N1O100O0010O1001OO2O2M2N`RY7"}, "grain_size": [[124, 0]]}, "382": {"grain_type": 1, "rle": {"size": [512, 512], "counts": "fme01n?1M4O1N2O0O2O1N2O1N1O1O2M3N2N2N2N2OO1O1O101N1O1O2N1O1O5K2M3M7J^Rj6"}, "grain_size": [[546, 0]]}, "389": {"grain_type": 1, "rle": {"size": [512, 512], "counts": "Snn02m?2N2O1N2N2N2N2N1O1O1N2N2O1O100000000O100O1O10O110O1O1O000O2N1O2N2N2N2N8I1OoQ^6"}, "grain_size": [[691, 0]]}, "401": {"grain_type": 1, "rle": {"size": [512, 512], "counts": "n=S1l>1O1O1000000000N3N1O2O1N2M2O2N2K5N2K5M3N2Mno_70_`_H2W?1e@5OHQ?5n@;P?<O0O2O1O1O000RB"}, "grain_size": [[911, 0]]}, "410": {"grain_type": 2, "rle": {"size": [512, 512], "counts": "k^P11k?5H8N2N1N3O001O1O00O1O1O100O1O1O1O1O1O002N1O1O1O2N4LaQb6"}, "grain_size": [[390, 0]]}, "419": {"grain_type": 1, "rle": {"size": [512, 512], "counts": "U_k02l?4M5K2N1O1O2N10O001O2O1O1N1O2N1O2N2KRQk6"}, "grain_size": [[222, 0]]}, "433": {"grain_type": 1, "rle": {"size": [512, 512], "counts": "Q?n0R?00001O000001O1N4L2N2M3N2N2O2N2M3N2M2Nlo\\71TPcH1N2N2M3N1N3N2N2O1O1N2N2N2M30O0000n@"}, "grain_size": [[745, 0]]}, "435": {"grain_type": 2, "rle": {"size": [512, 512], "counts": "eog01n?2N5K2N1O2N1O1O1010O0O1I8NbPQ7"}, "grain_size": [[153, 0]]}, "2": {"grain_type": 1, "rle": {"size": [512, 512], "counts": "0c0\\?1000O2O01O000105J1O1O2N1M4LTPd71jo[H4M3N1F91O0100000]O"}, "grain_size": [[356, 0]]}, "20": {"grain_type": 1, "rle": {"size": [512, 512], "counts": "e`g02m?2N2N2N2N3M6H4N2N00000011N2N2N1M4N2M3M3Ihom6"}, "grain_size": [[332, 0]]}, "29": {"grain_type": 1, "rle": {"size": [512, 512], "counts": "b`64j?3N9Y@HV?a001O1O001O010O001O00001O1O10O00010O0001O2O0O1O1O1O10O0O2N1O2N2N2N2N2N2N3M6K1N4LknS7"}, "grain_size": [[1179, 0]]}, "440": {"grain_type": 2, "rle": {"size": [512, 512], "counts": "P`l01m?5L2H:L2I7N1O2N2O1O1N2N1O001O01O2N1O1O2M4M3M2N2M4M3M2O1N2N2N2NY`c6"}, "grain_size": [[753, 0]]}, "356": {"grain_type": 2, "rle": {"size": [512, 512], "counts": "S=8e?4M2N201N2O1O001N01O1O1O10O0101Lc@C^?:6L4M3NYPe73_bZH"}, "grain_size": [[323, 0]]}, "364": {"grain_type": 1, "rle": {"size": [512, 512], "counts": "X]82l?3L4M3N1O1O3N1O1O001O1O01O0O100O2N1O4M6IhR]7"}, "grain_size": [[314, 0]]}, "383": {"grain_type": 1, "rle": {"size": [512, 512], "counts": "[=c0^?N1O1O2O1O1O001L8JVPf71foYH5L4L3N2N101000000eB"}, "grain_size": [[277, 0]]}, "363": {"grain_type": 1, "rle": {"size": [512, 512], "counts": "Pma03l?7J4K1O1N2O1O2N3O0O10OO0100O2O0O100O1O3M2M3N2N2N6JlRQ7"}, "grain_size": [[444, 0]]}, "360": {"grain_type": 1, "rle": {"size": [512, 512], "counts": "jlk02m?2N2N2N2N6J2N1O1O1O2O01O010O001N1O1O1N2O100O3M6J3MUSg6"}, "grain_size": [[394, 0]]}, "377": {"grain_type": 1, "rle": {"size": [512, 512], "counts": "WmS15j?2N2M7J2O0O1O1O1O0100O1^Og@<a?FSSe6"}, "grain_size": [[215, 0]]}, "366": {"grain_type": 1, "rle": {"size": [512, 512], "counts": "PmY13k?4Y@1X?<N3M3M3N1O1O2G801O1O1O1O00O2N100O1O1O1O0001O0010000001O1O1O1O100N2O1N2O2M4N0N2N2K5N1O3L3N2N2NQcm5"}, "grain_size": [[1509, 285]]}, "381": {"grain_type": 1, "rle": {"size": [512, 512], "counts": "im`17h?2N5L1N2N2N2N00010O100000O100O1O10001N0100O2O0O11N3K8J3I\\bP6"}, "grain_size": [[506, 0]]}, "387": {"grain_type": 1, "rle": {"size": [512, 512], "counts": "\\n\\11n?4L2N1O1O1O1O10O1O1O2N2M3NiQ\\6"}, "grain_size": [[106, 0]]}, "391": {"grain_type": 2, "rle": {"size": [512, 512], "counts": "o]i71n?2N2N20N2N2NRR3"}, "grain_size": [[25, 0]]}, "409": {"grain_type": 2, "rle": {"size": [512, 512], "counts": "ZnW74j?5L3M4L2O2M6J2O1N2M3M3O1O0010O02N1O2N2N1O0001O1O0000O2O0O200OO100O1O1N3N2FZAVOi>i0:YOQA6R?FTAOH0V?O\\R3"}, "grain_size": [[1452, 0]]}, "416": {"grain_type": 1, "rle": {"size": [512, 512], "counts": "Q_j72n?4K001O11N1O2NQa1"}, "grain_size": [[43, 0]]}, "425": {"grain_type": 1, "rle": {"size": [512, 512], "counts": "S_T14k?2N1O1O2O2M3M2N2N3M3M2N2N2N2N2N2N1O1O10O1O1000010O1N2O2N1O2M2I7H9M4L2N2MPQY6"}, "grain_size": [[910, 0]]}, "8": {"grain_type": 1, "rle": {"size": [512, 512], "counts": "PPZ71n?3M6J5K2N2M3O0O101O0O2N20000O1O1N3N1O1O1O1O00O000O10001O2N2O1N1O2O1O1M3L4M3N2E;OR`1"}, "grain_size": [[1023, 0]]}, "442": {"grain_type": 2, "rle": {"size": [512, 512], "counts": "d_`73j?4N1M30O10000000001O0O2N2N3M_P8"}, "grain_size": [[117, 0]]}}, "edges": {"(405, 4)": {}, "(405, 379)": {}, "(405, 380)": {}, "(405, 382)": {}, "(405, 389)": {}, "(405, 401)": {}, "(405, 410)": {}, "(405, 419)": {}, "(405, 433)": {}, "(405, 435)": {}, "(4, 2)": {}, "(4, 20)": {}, "(4, 29)": {}, "(4, 405)": {}, "(4, 433)": {}, "(4, 435)": {}, "(4, 440)": {}, "(379, 356)": {}, "(379, 364)": {}, "(379, 380)": {}, "(379, 383)": {}, "(379, 401)": {}, "(379, 405)": {}, "(380, 363)": {}, "(380, 364)": {}, "(380, 379)": {}, "(380, 382)": {}, "(380, 405)": {}, "(382, 360)": {}, "(382, 363)": {}, "(382, 377)": {}, "(382, 380)": {}, "(382, 389)": {}, "(382, 405)": {}, "(389, 366)": {}, "(389, 377)": {}, "(389, 381)": {}, "(389, 382)": {}, "(389, 387)": {}, "(389, 405)": {}, "(389, 410)": {}, "(401, 379)": {}, "(401, 383)": {}, "(401, 391)": {}, "(401, 405)": {}, "(401, 409)": {}, "(401, 416)": {}, "(401, 433)": {}, "(410, 387)": {}, "(410, 389)": {}, "(410, 405)": {}, "(410, 419)": {}, "(410, 425)": {}, "(419, 405)": {}, "(419, 410)": {}, "(419, 425)": {}, "(419, 435)": {}, "(419, 440)": {}, "(433, 2)": {}, "(433, 4)": {}, "(433, 8)": {}, "(433, 401)": {}, "(433, 405)": {}, "(433, 409)": {}, "(433, 416)": {}, "(433, 442)": {}, "(435, 4)": {}, "(435, 405)": {}, "(435, 419)": {}, "(435, 440)": {}, "(2, 4)": {}, "(2, 8)": {}, "(2, 29)": {}, "(2, 433)": {}, "(20, 4)": {}, "(20, 29)": {}, "(20, 440)": {}, "(29, 2)": {}, "(29, 4)": {}, "(29, 20)": {}, "(440, 4)": {}, "(440, 20)": {}, "(440, 419)": {}, "(440, 425)": {}, "(440, 435)": {}, "(356, 364)": {}, "(356, 379)": {}, "(356, 383)": {}, "(364, 356)": {}, "(364, 363)": {}, "(364, 379)": {}, "(364, 380)": {}, "(383, 356)": {}, "(383, 379)": {}, "(383, 391)": {}, "(383, 401)": {}, "(363, 360)": {}, "(363, 364)": {}, "(363, 380)": {}, "(363, 382)": {}, "(360, 363)": {}, "(360, 377)": {}, "(360, 382)": {}, "(377, 360)": {}, "(377, 366)": {}, "(377, 382)": {}, "(377, 389)": {}, "(366, 377)": {}, "(366, 381)": {}, "(366, 389)": {}, "(381, 366)": {}, "(381, 387)": {}, "(381, 389)": {}, "(387, 381)": {}, "(387, 389)": {}, "(387, 410)": {}, "(387, 425)": {}, "(391, 383)": {}, "(391, 401)": {}, "(391, 409)": {}, "(409, 391)": {}, "(409, 401)": {}, "(409, 416)": {}, "(409, 433)": {}, "(409, 442)": {}, "(416, 401)": {}, "(416, 409)": {}, "(416, 433)": {}, "(425, 387)": {}, "(425, 410)": {}, "(425, 419)": {}, "(425, 440)": {}, "(8, 2)": {}, "(8, 433)": {}, "(8, 442)": {}, "(442, 8)": {}, "(442, 409)": {}, "(442, 433)": {}}, "metadata": {"subgraph_metadata": [{"img_size": [512, 512], "grain_types": {"type_0": [[1.0, 0.0, 0.0], "candidate grain (white)"], "type_1": [[0.8944271802902222, 0.4472135901451111, 0.0], "low mobility (blue)"], "type_2": [[0.5773502588272095, 0.5773502588272095, 0.5773502588272095], "high mobility (red)"]}, "path": ["/media/ryan/TOSHIBA EXT/Research/datasets/AFRL_AGG/SPPARKS_simulations/candidate-grains/2021_02_02_16_33_candidate_grains_master/spparks_results/run_149"], "timesteps": [[0.0, 2000.0, 4000000.0]]}], "subgraph_node_ranges": [446]}}