{"nodes": {"380": {"grain_type": 0, "rle": {"size": [512, 512], "counts": "Unk5224a?8N4L4k@\\Og>P1O1O1O1N3N1N20000O1000O0O1O1001O0000000001O0001O01O00000001N100000001N10001O01K6L3N4_O?N2N2N2N2M3N3MaQY1"}, "grain_size": [[1890, 2929]]}, "337": {"grain_type": 1, "rle": {"size": [512, 512], "counts": "]m^51d?6_@L_?<N2N2N3M2O3L2N2N2N2N2O0O1O1O1O100O1001O100O100000000N1O2N101O001N4M1N1O2K6LmRm1"}, "grain_size": [[1267, 4080]]}, "341": {"grain_type": 1, "rle": {"size": [512, 512], "counts": "l]Q62j?5ZOK]A7b>e0N2M2O10000O1O1O1O1K501O0O100O2O00000O10O10001O1O1N2O1O1O1M3M3N2N=C7I3L3N2N_RZ1"}, "grain_size": [[1426, 0]]}, "347": {"grain_type": 1, "rle": {"size": [512, 512], "counts": "Tnc52i?6N1O1000000000O10000O2O001O1O1OoaS2"}, "grain_size": [[133, 0]]}, "363": {"grain_type": 1, "rle": {"size": [512, 512], "counts": "o]a63k?4M2N4L2N2M3N2N2N2O2N10O01OO00100O101O001O000000000O2O1O2N4K2N4K3N2N2N2OjQl0"}, "grain_size": [[723, 0]]}, "383": {"grain_type": 1, "rle": {"size": [512, 512], "counts": "jn`52^?9d@KZ?>O1O2N2O01O01O1O0000001N10001N010000O102VOPA`0Y?N4L4L[QR2"}, "grain_size": [[597, 0]]}, "389": {"grain_type": 1, "rle": {"size": [512, 512], "counts": "[_a64j?3N2A?N2N2N2N3L3N1O1O1001OO1O100O100000O10000001O0O2O1O1O1000N2N3M1O2N2N2N101O001N7FVQi0"}, "grain_size": [[1503, 1002]]}, "398": {"grain_type": 1, "rle": {"size": [512, 512], "counts": "Xof5;d?9C6O100N10O1O01000O01O02O1O1N2N2O2N1N2O1O1O1GmPm1"}, "grain_size": [[521, 0]]}, "408": {"grain_type": 1, "rle": {"size": [512, 512], "counts": "__R69d?4O1N1O2O100O1O1O2N1O1O0010O01O1O1OO1O2O0O1O1O1O2N10001N10001O1N2O1O1O1O2N1K\\PZ1"}, "grain_size": [[705, 0]]}, "329": {"grain_type": 1, "rle": {"size": [512, 512], "counts": "Zlf54k?2N2N2M4M2N2N2N2N2O100O1O001O0100O01O3M1O001O00O001N3N9H1O5J2N2N2N]Sh1"}, "grain_size": [[725, 0]]}, "332": {"grain_type": 1, "rle": {"size": [512, 512], "counts": "ilX52m?3M1O1O2N2M3N1O1O2N2O000000O00001O0010O01O1O002N100O2N4L2N2O1N`SW2"}, "grain_size": [[431, 0]]}, "344": {"grain_type": 2, "rle": {"size": [512, 512], "counts": "YmQ53i?5N7I4I5M4M2N2N3N0O2OO1O2N2N3M1O1O2L4N2N1O1O2N2N100O8HhR`2"}, "grain_size": [[627, 0]]}, "354": {"grain_type": 1, "rle": {"size": [512, 512], "counts": "nmV54k?2N1O1O2N1O1O1M3O1O1O3M2N1O101O10O1O10001M2N4L2N2N2M3J6NTbZ2"}, "grain_size": [[466, 0]]}, "316": {"grain_type": 1, "rle": {"size": [512, 512], "counts": "X\\\\63l?2M8I1I8N2N2O1N2N2N2O1N2O1N10O100O2N100O2O0O4L3N2M9G2N2N2N3KgST1"}, "grain_size": [[762, 0]]}, "321": {"grain_type": 2, "rle": {"size": [512, 512], "counts": "Q\\T62m?9G2N6J2O1N2N2O0O10O100O10001O0Ek@JW?4k@KV?2>NSda1"}, "grain_size": [[393, 0]]}, "338": {"grain_type": 1, "rle": {"size": [512, 512], "counts": "l\\c6<c?7J2M2N2O2M100O2N100O001O1O1O2L3N3O0O100000001O1O00O1O010O1O2N2N2N2O1N3M3N102M1O1O1O0O2M2N3N2N3L5KPcc0"}, "grain_size": [[1540, 3858]]}, "362": {"grain_type": 1, "rle": {"size": [512, 512], "counts": "hmo62m?5K2O3L2N2N2N2N2O0O1O2O010O1O1O001O01O103L3M1O1O1N8H5KjQb0"}, "grain_size": [[537, 0]]}, "372": {"grain_type": 1, "rle": {"size": [512, 512], "counts": "]^P72m?2M3N3M1O2O1O1O0010O01000N2O001O0O1O2N1O103LaQd0"}, "grain_size": [[252, 0]]}, "378": {"grain_type": 1, "rle": {"size": [512, 512], "counts": "hnR52f?9M4M2M3I7N1O2N3O0O0001N1N2O100000002N1O0O1O2N2O000O2N2N;C^Q^2"}, "grain_size": [[694, 0]]}, "405": {"grain_type": 1, "rle": {"size": [512, 512], "counts": "ToW5663U?=N2M3N2O1O1O001O1O1N2N3M2OO1O00011N2N1O101N2N10001O1N1O100\\OVA1l>MbQX2"}, "grain_size": [[984, 0]]}, "9": {"grain_type": 1, "rle": {"size": [512, 512], "counts": "V`o62h?7N2L5M2N2N2N1O3M2O2N2N1N2O2OO1N100O10000O2O1N100N3N2N1O2N2O1_Om@2Vo`0"}, "grain_size": [[808, 0]]}, "392": {"grain_type": 1, "rle": {"size": [512, 512], "counts": "i^V75c0O`>j0O1O000O1O1O1O2O1HnN_AS1a>6O2N2N10100000_NcA]1b>M3M2N4L2N3M2M3O1O1N2O2N2M2M3N2N2JZ@N`P8"}, "grain_size": [[1135, 5942]]}, "410": {"grain_type": 2, "rle": {"size": [512, 512], "counts": "j_e64j?3O001O001O1O1O001O2N1N2O0000O2O001O1O1N2I7NTPo0"}, "grain_size": [[257, 0]]}, "2": {"grain_type": 1, "rle": {"size": [512, 512], "counts": "UP_57h?2N7J1N3M1O2O1N1O1000000O1O101N1001N2WOQA>Q?@QA3L3^?Kd@4T_V2"}, "grain_size": [[478, 0]]}, "12": {"grain_type": 1, "rle": {"size": [512, 512], "counts": "P`h56i?2[@L[?6c@L[?b0J2O001N101N2O000O1O101O0O2O1O1O1000O1O0O2O1N2O1O1O2M2O1O0O2N1O2N2N2N2Gb@MW_d1"}, "grain_size": [[1086, 3863]]}, "4": {"grain_type": 2, "rle": {"size": [512, 512], "counts": "V`[6262]?;N0O2N1O1O1O2O000O101O000O1000O100000001O0O2N1O2M3N2L3O2N3M2Nj_T1"}, "grain_size": [[587, 0]]}}, "edges": {"(380, 337)": {}, "(380, 341)": {}, "(380, 347)": {}, "(380, 363)": {}, "(380, 383)": {}, "(380, 389)": {}, "(380, 398)": {}, "(380, 408)": {}, "(337, 329)": {}, "(337, 332)": {}, "(337, 341)": {}, "(337, 344)": {}, "(337, 347)": {}, "(337, 354)": {}, "(337, 380)": {}, "(341, 316)": {}, "(341, 321)": {}, "(341, 329)": {}, "(341, 337)": {}, "(341, 338)": {}, "(341, 363)": {}, "(341, 380)": {}, "(347, 337)": {}, "(347, 354)": {}, "(347, 380)": {}, "(347, 383)": {}, "(363, 338)": {}, "(363, 341)": {}, "(363, 362)": {}, "(363, 372)": {}, "(363, 380)": {}, "(363, 389)": {}, "(383, 347)": {}, "(383, 354)": {}, "(383, 378)": {}, "(383, 380)": {}, "(383, 398)": {}, "(383, 405)": {}, "(389, 9)": {}, "(389, 363)": {}, "(389, 372)": {}, "(389, 380)": {}, "(389, 392)": {}, "(389, 408)": {}, "(389, 410)": {}, "(398, 2)": {}, "(398, 12)": {}, "(398, 380)": {}, "(398, 383)": {}, "(398, 405)": {}, "(398, 408)": {}, "(408, 4)": {}, "(408, 12)": {}, "(408, 380)": {}, "(408, 389)": {}, "(408, 398)": {}, "(408, 410)": {}, "(329, 321)": {}, "(329, 332)": {}, "(329, 337)": {}, "(329, 341)": {}, "(332, 329)": {}, "(332, 337)": {}, "(332, 344)": {}, "(344, 332)": {}, "(344, 337)": {}, "(344, 354)": {}, "(354, 337)": {}, "(354, 344)": {}, "(354, 347)": {}, "(354, 378)": {}, "(354, 383)": {}, "(316, 321)": {}, "(316, 338)": {}, "(316, 341)": {}, "(321, 316)": {}, "(321, 329)": {}, "(321, 341)": {}, "(338, 316)": {}, "(338, 341)": {}, "(338, 362)": {}, "(338, 363)": {}, "(362, 338)": {}, "(362, 363)": {}, "(362, 372)": {}, "(362, 392)": {}, "(372, 362)": {}, "(372, 363)": {}, "(372, 389)": {}, "(372, 392)": {}, "(378, 354)": {}, "(378, 383)": {}, "(378, 405)": {}, "(405, 2)": {}, "(405, 378)": {}, "(405, 383)": {}, "(405, 398)": {}, "(9, 389)": {}, "(9, 392)": {}, "(9, 410)": {}, "(392, 9)": {}, "(392, 362)": {}, "(392, 372)": {}, "(392, 389)": {}, "(410, 4)": {}, "(410, 9)": {}, "(410, 389)": {}, "(410, 408)": {}, "(2, 12)": {}, "(2, 398)": {}, "(2, 405)": {}, "(12, 2)": {}, "(12, 4)": {}, "(12, 398)": {}, "(12, 408)": {}, "(4, 12)": {}, "(4, 408)": {}, "(4, 410)": {}}, "metadata": {"subgraph_metadata": [{"img_size": [512, 512], "grain_types": {"type_0": [[1.0, 0.0, 0.0], "candidate grain (white)"], "type_1": [[0.8944271802902222, 0.4472135901451111, 0.0], "low mobility (blue)"], "type_2": [[0.5773502588272095, 0.5773502588272095, 0.5773502588272095], "high mobility (red)"]}, "path": ["/media/ryan/TOSHIBA EXT/Research/datasets/AFRL_AGG/SPPARKS_simulations/candidate-grains/2021_01_28_08_21_candidate_grains_master/spparks_results/run_48"], "timesteps": [[0.0, 2000.0, 4000000.0]]}], "subgraph_node_ranges": [417]}}