{"nodes": {"397": {"grain_type": 0, "rle": {"size": [512, 512], "counts": "Y^l22f?9J6HAj@b0U?6N2N2N2N2N2O1N2O1N3M2N2M3N3L2O001O100001O001O00O01O1O00101O1O1O1O2N2N1O2M2N2N3M2N2M3M5J4N4Ea@Mb?1`@Le?0VbY4"}, "grain_size": [[2051, 12744]]}, "361": {"grain_type": 1, "rle": {"size": [512, 512], "counts": "Q]\\32k?4N2N2L4M4M3M2O2M2N2O2M2N2N2N4L2N4L2N4L2O000N2N20O01001O1N2N2N2N2N2cNaAV1g>M2O2N1O1O1O001N10000O1YOUA8m>CYA5_?McRk3"}, "grain_size": [[1761, 1282]]}, "368": {"grain_type": 1, "rle": {"size": [512, 512], "counts": "^]h22m?2N2I6M3N3N2K4O1O1O2N10O1O2N1O1O2N2O1N101N2N1O1N2O2M3N1O2NPch4"}, "grain_size": [[495, 0]]}, "371": {"grain_type": 1, "rle": {"size": [512, 512], "counts": "Q]W32m?1O2N101O0O02O000O1NTSc4"}, "grain_size": [[57, 0]]}, "396": {"grain_type": 1, "rle": {"size": [512, 512], "counts": "Snd32m?2N2OO1O10oQX4"}, "grain_size": [[25, 0]]}, "406": {"grain_type": 1, "rle": {"size": [512, 512], "counts": "Un_25j?2N2O1O1N3K4N4J3N2N1N20001O000100O2O1N100O2O1O0O1N2H9J7K\\bQ5"}, "grain_size": [[614, 0]]}, "411": {"grain_type": 1, "rle": {"size": [512, 512], "counts": "lnY34k?1O2N2N2O1O001O00000001N2MXQ_4"}, "grain_size": [[144, 0]]}, "423": {"grain_type": 1, "rle": {"size": [512, 512], "counts": "U__31b?0i@2U?0h@3V?`0K2N3M1N3M3L3O2M3M110O1O10000001O1O2M1O2O1O1O2M3N0O2O100O1O001O0O1O3M4L2N3M2M6J3Nn`j3"}, "grain_size": [[1272, 3537]]}, "425": {"grain_type": 1, "rle": {"size": [512, 512], "counts": "]oc22U?OQA165g>6UAKj>f0O010O1O100O010O100O01000O01O2O1N101O1O1O1O100M3L4N2N3M2M3M3NVQk4"}, "grain_size": [[829, 0]]}, "429": {"grain_type": 1, "rle": {"size": [512, 512], "counts": "YoP32k?4N3M2N3L3M3N2N2O2M10001O001O000004L001O1O1O1O0O2N1M3O101N2O1N5K2NdP^4"}, "grain_size": [[636, 0]]}, "323": {"grain_type": 2, "rle": {"size": [512, 512], "counts": "gk]35i?4M3M2N100O1O001O1N2O2O1O0O1O2N1N2O2O010O10O1N1M3O1O1N2O1O1O1O2N101N3L3IZ@N]TP4"}, "grain_size": [[751, 0]]}, "338": {"grain_type": 1, "rle": {"size": [512, 512], "counts": "Rli33l?2N2M3N2N2N2N2N2OO101O1N2N2N2M3MSdm3"}, "grain_size": [[218, 0]]}, "350": {"grain_type": 1, "rle": {"size": [512, 512], "counts": "Xl[32m?4L3M3M2N3M2N2OO100O00100O1O2N2N1O1O2N1O1O2O001MmcW4"}, "grain_size": [[322, 0]]}, "353": {"grain_type": 1, "rle": {"size": [512, 512], "counts": "clP37g?3N2M2L5N2N1O10001O1O001O00O1O1O10001N110O1O3M2N2M2N3K4M]c`4"}, "grain_size": [[540, 0]]}, "357": {"grain_type": 1, "rle": {"size": [512, 512], "counts": "_\\m32l?4M2O2N1N2N20O103L2N1O1O1O1N[Sk3"}, "grain_size": [[132, 0]]}, "364": {"grain_type": 2, "rle": {"size": [512, 512], "counts": "P]S48b?I_@=^?6K5M3M4L1O0001O000001O0O10001N101N1O2N2N2N2OO001O2O1N1O101O0J7N1L5N2M3N3L4M2N3M3MQSW3"}, "grain_size": [[1323, 2284]]}, "390": {"grain_type": 1, "rle": {"size": [512, 512], "counts": "`mS47i?1O03M]Rj3"}, "grain_size": [[28, 0]]}, "400": {"grain_type": 1, "rle": {"size": [512, 512], "counts": "Qng34l?0O2O1O2N0O2N2N2N3M3M1O2O1O1O1O001O0O1000O00011N2O0O1O002YOj@a0]?M5K5Kkag3"}, "grain_size": [[642, 0]]}, "359": {"grain_type": 1, "rle": {"size": [512, 512], "counts": "ll_24k?2N9F3N3M2N2N2N2N2N2N2O00O001O10OO2O2N1J7L4M3N3J6M2N2NYSR5"}, "grain_size": [[617, 0]]}, "360": {"grain_type": 1, "rle": {"size": [512, 512], "counts": "[lh23j?4O0O2N2N2N3N2N1O1N100O101N1O10J7M3N2M2L4O2N2NlSk4"}, "grain_size": [[338, 0]]}, "384": {"grain_type": 1, "rle": {"size": [512, 512], "counts": "g]X21o?5K4K2N1O1M3O1O1O100O101N2O1N1O0002O2N1N2L4N2L4M3M3L`RZ5"}, "grain_size": [[446, 0]]}, "403": {"grain_type": 1, "rle": {"size": [512, 512], "counts": "lnm12k?4M3L4N2L3N10010O00010O100O1O1O1O100O1O1O1O101O1O00O100O1O1O1O1O2O1O1N6J2N2N2N2N3N1O_a\\5"}, "grain_size": [[836, 0]]}, "419": {"grain_type": 1, "rle": {"size": [512, 512], "counts": "P_Z21n?2S@7a?5N1O1O2N2N2O1O1N000000001O100000O1O2]Oj@6e?LQaZ5"}, "grain_size": [[458, 0]]}, "416": {"grain_type": 2, "rle": {"size": [512, 512], "counts": "enQ42m?4L2O2M2O4K2N1O1O1O0000100001O1OO01O1O2N106I^ab3"}, "grain_size": [[379, 0]]}, "430": {"grain_type": 1, "rle": {"size": [512, 512], "counts": "]_Q42m?2N2N4L2M3M4M2N2O1O1N1O2O1O1O00O10O001O1O100O1001O1N1O3M2O1N2O1N2O1N2N5LeP\\3"}, "grain_size": [[851, 0]]}, "432": {"grain_type": 1, "rle": {"size": [512, 512], "counts": "cod32m?2O1O1O1O00O1000001N^`U4"}, "grain_size": [[59, 0]]}, "436": {"grain_type": 1, "rle": {"size": [512, 512], "counts": "aoi32m?5L1O001N2O1N2O100O1O00O1O011O1N2N4M1N2N[`k3"}, "grain_size": [[228, 0]]}, "444": {"grain_type": 2, "rle": {"size": [512, 512], "counts": "ho\\32m?2L4N2O2M2O1N2N2N100001N2N1O2O3L2N2N2N2MY`X4"}, "grain_size": [[253, 0]]}, "435": {"grain_type": 2, "rle": {"size": [512, 512], "counts": "i_b22m?2M4J5M4N1O1N2O1O1O1O2M2O00O1O001O1O01O2O0O10O100O1O101O001O2M2O2L3K5L4N2N\\`j4"}, "grain_size": [[765, 0]]}, "440": {"grain_type": 1, "rle": {"size": [512, 512], "counts": "co^23l?2N2N2N2O0000O1O0O3Ke`[5"}, "grain_size": [[87, 0]]}, "10": {"grain_type": 1, "rle": {"size": [512, 512], "counts": "PPS32j?6K4N5K2O1O1O100O2OO0000000001O00O1O1O2N2O1N2N3N1N2O1O1N1MPP^4"}, "grain_size": [[511, 0]]}}, "edges": {"(397, 361)": {}, "(397, 368)": {}, "(397, 371)": {}, "(397, 396)": {}, "(397, 406)": {}, "(397, 411)": {}, "(397, 423)": {}, "(397, 425)": {}, "(397, 429)": {}, "(361, 323)": {}, "(361, 338)": {}, "(361, 350)": {}, "(361, 353)": {}, "(361, 357)": {}, "(361, 364)": {}, "(361, 371)": {}, "(361, 390)": {}, "(361, 396)": {}, "(361, 397)": {}, "(361, 400)": {}, "(368, 353)": {}, "(368, 359)": {}, "(368, 360)": {}, "(368, 371)": {}, "(368, 397)": {}, "(368, 406)": {}, "(371, 353)": {}, "(371, 361)": {}, "(371, 368)": {}, "(371, 397)": {}, "(396, 361)": {}, "(396, 397)": {}, "(396, 400)": {}, "(396, 423)": {}, "(406, 359)": {}, "(406, 368)": {}, "(406, 384)": {}, "(406, 397)": {}, "(406, 403)": {}, "(406, 419)": {}, "(406, 425)": {}, "(411, 397)": {}, "(411, 423)": {}, "(411, 429)": {}, "(423, 396)": {}, "(423, 397)": {}, "(423, 400)": {}, "(423, 411)": {}, "(423, 416)": {}, "(423, 429)": {}, "(423, 430)": {}, "(423, 432)": {}, "(423, 436)": {}, "(423, 444)": {}, "(425, 397)": {}, "(425, 406)": {}, "(425, 419)": {}, "(425, 429)": {}, "(425, 435)": {}, "(425, 440)": {}, "(429, 10)": {}, "(429, 397)": {}, "(429, 411)": {}, "(429, 423)": {}, "(429, 425)": {}, "(429, 435)": {}, "(429, 444)": {}, "(323, 338)": {}, "(323, 350)": {}, "(323, 361)": {}, "(338, 323)": {}, "(338, 357)": {}, "(338, 361)": {}, "(350, 323)": {}, "(350, 353)": {}, "(350, 361)": {}, "(353, 350)": {}, "(353, 360)": {}, "(353, 361)": {}, "(353, 368)": {}, "(353, 371)": {}, "(357, 338)": {}, "(357, 361)": {}, "(357, 364)": {}, "(364, 357)": {}, "(364, 361)": {}, "(364, 390)": {}, "(364, 400)": {}, "(390, 361)": {}, "(390, 364)": {}, "(390, 400)": {}, "(400, 361)": {}, "(400, 364)": {}, "(400, 390)": {}, "(400, 396)": {}, "(400, 416)": {}, "(400, 423)": {}, "(359, 360)": {}, "(359, 368)": {}, "(359, 384)": {}, "(359, 406)": {}, "(360, 353)": {}, "(360, 359)": {}, "(360, 368)": {}, "(384, 359)": {}, "(384, 403)": {}, "(384, 406)": {}, "(403, 384)": {}, "(403, 406)": {}, "(403, 419)": {}, "(419, 403)": {}, "(419, 406)": {}, "(419, 425)": {}, "(419, 440)": {}, "(416, 400)": {}, "(416, 423)": {}, "(416, 430)": {}, "(430, 416)": {}, "(430, 423)": {}, "(430, 436)": {}, "(432, 423)": {}, "(432, 436)": {}, "(432, 444)": {}, "(436, 423)": {}, "(436, 430)": {}, "(436, 432)": {}, "(444, 10)": {}, "(444, 423)": {}, "(444, 429)": {}, "(444, 432)": {}, "(435, 10)": {}, "(435, 425)": {}, "(435, 429)": {}, "(435, 440)": {}, "(440, 419)": {}, "(440, 425)": {}, "(440, 435)": {}, "(10, 429)": {}, "(10, 435)": {}, "(10, 444)": {}}, "metadata": {"subgraph_metadata": [{"img_size": [512, 512], "grain_types": {"type_0": [[1.0, 0.0, 0.0], "candidate grain (white)"], "type_1": [[0.8944271802902222, 0.4472135901451111, 0.0], "low mobility (blue)"], "type_2": [[0.5773502588272095, 0.5773502588272095, 0.5773502588272095], "high mobility (red)"]}, "path": ["/media/ryan/TOSHIBA EXT/Research/datasets/AFRL_AGG/SPPARKS_simulations/candidate-grains/2021_01_14_06_43_candidate_grains_master/spparks_results/run_170"], "timesteps": [[0.0, 2000.0, 4000000.0]]}], "subgraph_node_ranges": [448]}}