{"nodes": {"121": {"grain_type": 0, "rle": {"size": [512, 512], "counts": "_dX6b0\\?3N2N2O1N2N2N3M5UAlNa>_1J2O1N2N001O1O01O1O0100O1001O1O1O1N10001O01O01O1O001O1O1O1O1O1O000O1O1N2L6M2M4I9K2N2Eb@1ijm0"}, "grain_size": [[2214, 32800]]}, "86": {"grain_type": 1, "rle": {"size": [512, 512], "counts": "ac\\64j?3N3K5L3O3M1O1O0001O0\\Oh@?]?00O9H1K]\\[1"}, "grain_size": [[251, 0]]}, "100": {"grain_type": 1, "rle": {"size": [512, 512], "counts": "mSU6:e?2K5O1O1O001N2O0O000100O1O002N2N3M3N1N4L2N2NQ\\_1"}, "grain_size": [[362, 0]]}, "102": {"grain_type": 1, "rle": {"size": [512, 512], "counts": "jSd65j?2N2O1O000O2N1O1O2N2N101N2N2N200O1O0001O00000O2N1O1O1O2M4L3N1O2N2N2NX\\j0"}, "grain_size": [[600, 0]]}, "110": {"grain_type": 2, "rle": {"size": [512, 512], "counts": "Zdo63l?2N3M5K2M3M2O1O1O2N1O1M3O2O1O0000N2O1O2N8H2N6H4Klkc0"}, "grain_size": [[514, 0]]}, "117": {"grain_type": 1, "rle": {"size": [512, 512], "counts": "jTf52j?6J5M3M2O2O1N2O1O1O00100N2N2O0O2O001N10O10O01O1O1O010O1O011O1N2O1N2O0O2N2^OTlf1"}, "grain_size": [[951, 0]]}, "119": {"grain_type": 1, "rle": {"size": [512, 512], "counts": "jTR74h?8L1O01O00000O2N2N1O1O2N2NVkf0"}, "grain_size": [[120, 0]]}, "130": {"grain_type": 1, "rle": {"size": [512, 512], "counts": "[Uo53m?4K2O5J2N2N1O2O0O1O1000O0100O10O00002O1O1O1O1O1N2O2N4F[@1XZc1"}, "grain_size": [[508, 0]]}, "144": {"grain_type": 1, "rle": {"size": [512, 512], "counts": "eem62m?2M4J5N1N3J6N00001O11N1O1N2O1O8H7J`Zi0"}, "grain_size": [[292, 0]]}, "163": {"grain_type": 1, "rle": {"size": [512, 512], "counts": "jeV67h?3M2N2b@IQ?c001O1O000O101O00O2DRACP?9>M6KTj`1"}, "grain_size": [[354, 0]]}, "166": {"grain_type": 2, "rle": {"size": [512, 512], "counts": "XV]66g?6K2GEl@<S?901O1N1O2N2O002N1O1O1O00O010001O01O0000000O1O1O1O1O1O1O101N2N3M2N1Bh@3Z?Ik@4c?M2NgYn0"}, "grain_size": [[1116, 0]]}, "69": {"grain_type": 1, "rle": {"size": [512, 512], "counts": "dR\\6<c?2N2N4M1N3M2O0O1O1O1O2N101OO10000O2N101O1O1O2N1O1N2K4O1M4M2N3O1N[]S1"}, "grain_size": [[742, 0]]}, "85": {"grain_type": 2, "rle": {"size": [512, 512], "counts": "Ycm54k?101N2N2N2N2O000O1O2N2N2N1O1O2N2N2N1O1O1N20O100O1O100000:E2L4M5L2L5Ljl`1"}, "grain_size": [[698, 0]]}, "93": {"grain_type": 1, "rle": {"size": [512, 512], "counts": "\\Sb62m?1O108H1N3M01000000O1O1O002N5K3N1NblT1"}, "grain_size": [[192, 0]]}, "97": {"grain_type": 1, "rle": {"size": [512, 512], "counts": "occ52m?4L3M2N2M3M2O2L4N2N2O01N010000O101N000010O2O1O1N2O1O0O10001O1N2O000O2F:NZli1"}, "grain_size": [[780, 0]]}, "80": {"grain_type": 1, "rle": {"size": [512, 512], "counts": "SSi65j?5I5L3M3OO02L3000001O0000001O0000001N10O1N2O2N3J7M1N2N2N4L3Mm\\g0"}, "grain_size": [[623, 0]]}, "87": {"grain_type": 1, "rle": {"size": [512, 512], "counts": "ccR72m?2M2O2N2K5O1N001O1O1O100001O0O2M2O2O2M2N2N5L`la0"}, "grain_size": [[296, 0]]}, "98": {"grain_type": 1, "rle": {"size": [512, 512], "counts": "icY71n?8G3N6K1N3M1O100O10001O1O000O10O2N2O1N2N1O1O2O0Ibl9"}, "grain_size": [[519, 0]]}, "118": {"grain_type": 2, "rle": {"size": [512, 512], "counts": "gTX73l?2N2N2N001M3L4O1000O1000001O1N1O1O3L3Kek="}, "grain_size": [[243, 0]]}, "120": {"grain_type": 1, "rle": {"size": [512, 512], "counts": "_d]55e?M^@5`?7N3N3M00001N001O1O1001O2N1O1O1N1L5K5M3Mf[W2"}, "grain_size": [[368, 0]]}, "136": {"grain_type": 1, "rle": {"size": [512, 512], "counts": "Ue\\52m?3M4J4M3M6K2O1O100N3N2N1O1O0000O1000101N1O1O01000000000O001N2N2N2N1O2O004K5L1N6JYjn1"}, "grain_size": [[952, 0]]}, "131": {"grain_type": 1, "rle": {"size": [512, 512], "counts": "ReU78g?7I5K1O2N2N10100N2O00O1O1O10O01O1O100O2N4L2N2O2K4LoZ="}, "grain_size": [[560, 0]]}, "152": {"grain_type": 2, "rle": {"size": [512, 512], "counts": "QVk51n?3M2N2_@JU?b0N2O1O1N2O0O1O0101O001N1O100000O100007H3M2O1IQZg1"}, "grain_size": [[529, 0]]}, "153": {"grain_type": 1, "rle": {"size": [512, 512], "counts": "Qfo64i?5M3M2N2O1O1N2N2M3N1O2N2O0000O2O1O0O2N2N2N5K2M3N4K3Nnib0"}, "grain_size": [[522, 0]]}, "178": {"grain_type": 1, "rle": {"size": [512, 512], "counts": "dV\\63l?2N5K2O1O0001000O01O1N1O3N1N2MYi[1"}, "grain_size": [[153, 0]]}, "180": {"grain_type": 1, "rle": {"size": [512, 512], "counts": "PWm52m?2N8H1HEh@>X?500O100000O01O10001O0000000O1O1001O0K6N2N1O1O1O2N4K3NYib1"}, "grain_size": [[585, 0]]}, "172": {"grain_type": 1, "rle": {"size": [512, 512], "counts": "jVi61n?2N3M2N2N1O1O100O0000001O00000010M4N2N2N2N2NaYk0"}, "grain_size": [[229, 0]]}, "190": {"grain_type": 2, "rle": {"size": [512, 512], "counts": "PW`63m?1O2M2N4M1N2M3N2O2M1000100OO1O100N3L4N3M2LTiT1"}, "grain_size": [[350, 0]]}}, "edges": {"(121, 86)": {}, "(121, 100)": {}, "(121, 102)": {}, "(121, 110)": {}, "(121, 117)": {}, "(121, 119)": {}, "(121, 130)": {}, "(121, 144)": {}, "(121, 163)": {}, "(121, 166)": {}, "(86, 69)": {}, "(86, 85)": {}, "(86, 93)": {}, "(86, 100)": {}, "(86, 102)": {}, "(86, 121)": {}, "(100, 85)": {}, "(100, 86)": {}, "(100, 97)": {}, "(100, 117)": {}, "(100, 121)": {}, "(102, 80)": {}, "(102, 86)": {}, "(102, 87)": {}, "(102, 93)": {}, "(102, 110)": {}, "(102, 121)": {}, "(110, 87)": {}, "(110, 98)": {}, "(110, 102)": {}, "(110, 118)": {}, "(110, 119)": {}, "(110, 121)": {}, "(117, 97)": {}, "(117, 100)": {}, "(117, 120)": {}, "(117, 121)": {}, "(117, 130)": {}, "(117, 136)": {}, "(119, 110)": {}, "(119, 118)": {}, "(119, 121)": {}, "(119, 131)": {}, "(119, 144)": {}, "(130, 117)": {}, "(130, 121)": {}, "(130, 136)": {}, "(130, 152)": {}, "(130, 163)": {}, "(144, 119)": {}, "(144, 121)": {}, "(144, 131)": {}, "(144, 153)": {}, "(144, 166)": {}, "(163, 121)": {}, "(163, 130)": {}, "(163, 152)": {}, "(163, 166)": {}, "(163, 178)": {}, "(163, 180)": {}, "(166, 121)": {}, "(166, 144)": {}, "(166, 153)": {}, "(166, 163)": {}, "(166, 172)": {}, "(166, 178)": {}, "(166, 190)": {}, "(69, 80)": {}, "(69, 85)": {}, "(69, 86)": {}, "(69, 93)": {}, "(85, 69)": {}, "(85, 86)": {}, "(85, 97)": {}, "(85, 100)": {}, "(93, 69)": {}, "(93, 80)": {}, "(93, 86)": {}, "(93, 102)": {}, "(97, 85)": {}, "(97, 100)": {}, "(97, 117)": {}, "(97, 120)": {}, "(80, 69)": {}, "(80, 87)": {}, "(80, 93)": {}, "(80, 102)": {}, "(87, 80)": {}, "(87, 98)": {}, "(87, 102)": {}, "(87, 110)": {}, "(98, 87)": {}, "(98, 110)": {}, "(98, 118)": {}, "(118, 98)": {}, "(118, 110)": {}, "(118, 119)": {}, "(118, 131)": {}, "(120, 97)": {}, "(120, 117)": {}, "(120, 136)": {}, "(136, 117)": {}, "(136, 120)": {}, "(136, 130)": {}, "(136, 152)": {}, "(131, 118)": {}, "(131, 119)": {}, "(131, 144)": {}, "(131, 153)": {}, "(152, 130)": {}, "(152, 136)": {}, "(152, 163)": {}, "(152, 180)": {}, "(153, 131)": {}, "(153, 144)": {}, "(153, 166)": {}, "(153, 172)": {}, "(178, 163)": {}, "(178, 166)": {}, "(178, 180)": {}, "(178, 190)": {}, "(180, 152)": {}, "(180, 163)": {}, "(180, 178)": {}, "(172, 153)": {}, "(172, 166)": {}, "(172, 190)": {}, "(190, 166)": {}, "(190, 172)": {}, "(190, 178)": {}}, "metadata": {"subgraph_metadata": [{"img_size": [512, 512], "grain_types": {"type_0": [[1.0, 0.0, 0.0], "candidate grain (white)"], "type_1": [[0.8944271802902222, 0.4472135901451111, 0.0], "low mobility (blue)"], "type_2": [[0.5773502588272095, 0.5773502588272095, 0.5773502588272095], "high mobility (red)"]}, "path": ["/media/ryan/TOSHIBA EXT/Research/datasets/AFRL_AGG/SPPARKS_simulations/candidate-grains/2021_01_19_22_22_candidate_grains_master/spparks_results/run_395"], "timesteps": [[0.0, 2000.0, 4000000.0]]}], "subgraph_node_ranges": [432]}}