{"nodes": {"154": {"grain_type": 0, "rle": {"size": [512, 512], "counts": "ldZ62m?2N3M2l@J[>9bAI\\>:aAH]>;\\AKb>k0O1O3M1N10000001OO2O0O10000000000O1O0100O10000O1M3O1O1O2N2M3N2N2N1O2N2N2N4L2N2N2N2O1F]@4cjl0"}, "grain_size": [[1743, 34075]]}, "121": {"grain_type": 1, "rle": {"size": [512, 512], "counts": "WTZ63g?7O1O1N1O2N2N3M5K1O100O001O100O2N001O01000001O1O0O1O100000001O1O1O1O9E3M3N3Mk[R1"}, "grain_size": [[909, 0]]}, "127": {"grain_type": 1, "rle": {"size": [512, 512], "counts": "_dk62l?3N2N2N2001N2M2Lcko0"}, "grain_size": [[62, 0]]}, "129": {"grain_type": 1, "rle": {"size": [512, 512], "counts": "gdQ63l?2N2M3N1O0O2O1N20O100001N10000O1010N2N2N1O2N2N3M`ka1"}, "grain_size": [[319, 0]]}, "130": {"grain_type": 2, "rle": {"size": [512, 512], "counts": "eTo62k?4M3N4M1N2O1O1O1N2N1000000010O0001N1O2N10O01O001000O10O0001O2O0O2J6M3Ea@M\\[?"}, "grain_size": [[747, 0]]}, "151": {"grain_type": 1, "rle": {"size": [512, 512], "counts": "PeR62m?f0YO4M3N00O11N100001O0O1000001O1O1N3N1L5M3M3Imja1"}, "grain_size": [[589, 0]]}, "157": {"grain_type": 1, "rle": {"size": [512, 512], "counts": "SUS72m?8I1O001O100O00O2N1J7Mmjf0"}, "grain_size": [[112, 0]]}, "165": {"grain_type": 1, "rle": {"size": [512, 512], "counts": "Pfi62k?5M3M2N2N2M2O2N1O1O1O2N2N1O2N1O1O100O11N2O0O2O1N2O010N2N2L4N3M5J3N2N2NTZd0"}, "grain_size": [[758, 0]]}, "169": {"grain_type": 1, "rle": {"size": [512, 512], "counts": "nUS61m?3N2O0O200O2N2N1O1N2O1O1O1O1O1N1000O2K5N2K5O1N4LPZ`1"}, "grain_size": [[313, 0]]}, "177": {"grain_type": 1, "rle": {"size": [512, 512], "counts": "_f[61n?3J5N3J5O1N2N2N3N1O1O000001N1O1O1O1O1O100000O10O001O1O2L5M3M2L4NiiS1"}, "grain_size": [[594, 0]]}, "100": {"grain_type": 1, "rle": {"size": [512, 512], "counts": "^cb61n?2N3N1N1O1O2N2N1M3O1O1001O100O1N5K7J1N`\\S1"}, "grain_size": [[229, 0]]}, "102": {"grain_type": 1, "rle": {"size": [512, 512], "counts": "fcV63l?2M3N3M2M3N2N2M2O1O10O1O1O1O2N2N1O101N1O2N101N2N2N3M_l[1"}, "grain_size": [[377, 0]]}, "118": {"grain_type": 2, "rle": {"size": [512, 512], "counts": "fSj61n?2N2O9F2N2O2N4L101N2O00O1N100O1000000O1O101O000010O0000O2N2N2O2M2N2N2O1O002M2Nmka0"}, "grain_size": [[696, 0]]}, "126": {"grain_type": 1, "rle": {"size": [512, 512], "counts": "Ydc53d?Nb@4]?0_@2_?9N2M3K5M201N2O0O101N2N2O1O00001O1O1O2N0000O1O2O1O1L3O2N1N2O1O2M3N1N202N1O1O2M2O1O1N2LR\\e1"}, "grain_size": [[1270, 0]]}, "164": {"grain_type": 1, "rle": {"size": [512, 512], "counts": "cUa53l?2N4L2N101O1O0O2N1O2N2O0O1O1O1O2N2N2N10000N3M2O1O001O10O01O01000010N2nNWAj0k>TOkA5S?LYjk1"}, "grain_size": [[960, 0]]}, "94": {"grain_type": 2, "rle": {"size": [512, 512], "counts": "gcX72m?2N2N3M2N2O1N2N1O3M2N2O1N101N2O10N2N2O001Hi@EW?3`0Mb\\;"}, "grain_size": [[437, 0]]}, "135": {"grain_type": 1, "rle": {"size": [512, 512], "counts": "id_75i?2FLb@:Y?:N2O001O10O100O1O1N2N1O2N2M2O4L6J2NYk5"}, "grain_size": [[373, 0]]}, "159": {"grain_type": 2, "rle": {"size": [512, 512], "counts": "_UW72m?2I7M3N3M5L1N2O1O1N101N1O1O100O10O10001N2N1O2N2N1\\Oj@=X?Ak@<`?J[@Jj?1bZ:"}, "grain_size": [[658, 0]]}, "186": {"grain_type": 2, "rle": {"size": [512, 512], "counts": "Pg`62k?301O0O2N1O2N2N2N2O1O001O1N1O001O1M4N1O2L4N3M2O01O0O1001000O001O000O100O10O01O0O2O001GPAAR?8UAER?4QAIR?1Pjg0"}, "grain_size": [[1180, 0]]}, "195": {"grain_type": 1, "rle": {"size": [512, 512], "counts": "PWV71i?7_ONPA5n>Ml@8Q?=O1O1N3N2N1O1O1010O000001O1O0O2O0102M1N2O1O1N2N6J3N1N2N3M2O3M1N2O3L4LSY6"}, "grain_size": [[1116, 0]]}, "197": {"grain_type": 1, "rle": {"size": [512, 512], "counts": "dfi52l?3M4M2N6J2K7HWOQAP1i>5O1XAnN`>Y1O2O0O2O0001M11O0002N2N101N2O2M3N1N2N2O1N2O1O1O1O001N3N1O2N1N2N2O1N3M2N2MUi^1"}, "grain_size": [[1389, 0]]}}, "edges": {"(154, 121)": {}, "(154, 127)": {}, "(154, 129)": {}, "(154, 130)": {}, "(154, 151)": {}, "(154, 157)": {}, "(154, 165)": {}, "(154, 169)": {}, "(154, 177)": {}, "(121, 100)": {}, "(121, 102)": {}, "(121, 118)": {}, "(121, 126)": {}, "(121, 127)": {}, "(121, 129)": {}, "(121, 154)": {}, "(127, 118)": {}, "(127, 121)": {}, "(127, 130)": {}, "(127, 154)": {}, "(129, 121)": {}, "(129, 126)": {}, "(129, 151)": {}, "(129, 154)": {}, "(129, 164)": {}, "(130, 94)": {}, "(130, 118)": {}, "(130, 127)": {}, "(130, 135)": {}, "(130, 154)": {}, "(130, 157)": {}, "(130, 159)": {}, "(151, 129)": {}, "(151, 154)": {}, "(151, 164)": {}, "(151, 169)": {}, "(157, 130)": {}, "(157, 154)": {}, "(157, 159)": {}, "(157, 165)": {}, "(165, 154)": {}, "(165, 157)": {}, "(165, 159)": {}, "(165, 177)": {}, "(165, 186)": {}, "(165, 195)": {}, "(169, 151)": {}, "(169, 154)": {}, "(169, 164)": {}, "(169, 177)": {}, "(169, 197)": {}, "(177, 154)": {}, "(177, 165)": {}, "(177, 169)": {}, "(177, 186)": {}, "(177, 197)": {}, "(100, 102)": {}, "(100, 118)": {}, "(100, 121)": {}, "(102, 100)": {}, "(102, 121)": {}, "(102, 126)": {}, "(118, 94)": {}, "(118, 100)": {}, "(118, 121)": {}, "(118, 127)": {}, "(118, 130)": {}, "(126, 102)": {}, "(126, 121)": {}, "(126, 129)": {}, "(126, 164)": {}, "(164, 126)": {}, "(164, 129)": {}, "(164, 151)": {}, "(164, 169)": {}, "(164, 197)": {}, "(94, 118)": {}, "(94, 130)": {}, "(94, 135)": {}, "(135, 94)": {}, "(135, 130)": {}, "(135, 159)": {}, "(159, 130)": {}, "(159, 135)": {}, "(159, 157)": {}, "(159, 165)": {}, "(159, 195)": {}, "(186, 165)": {}, "(186, 177)": {}, "(186, 195)": {}, "(186, 197)": {}, "(195, 159)": {}, "(195, 165)": {}, "(195, 186)": {}, "(197, 164)": {}, "(197, 169)": {}, "(197, 177)": {}, "(197, 186)": {}}, "metadata": {"subgraph_metadata": [{"img_size": [512, 512], "grain_types": {"type_0": [[1.0, 0.0, 0.0], "candidate grain (white)"], "type_1": [[0.8944271802902222, 0.4472135901451111, 0.0], "low mobility (blue)"], "type_2": [[0.5773502588272095, 0.5773502588272095, 0.5773502588272095], "high mobility (red)"]}, "path": ["/media/ryan/TOSHIBA EXT/Research/datasets/AFRL_AGG/SPPARKS_simulations/candidate-grains/2021_01_01_00_18_candidate_grains_master/spparks_results/run_669"], "timesteps": [[0.0, 2000.0, 4000000.0]]}], "subgraph_node_ranges": [447]}}